human_seconds/__init__.py
human_seconds/converter.py
human_seconds-0.1.2.dist-info/licenses/LICENCE
human_seconds-0.1.2.dist-info/METADATA
human_seconds-0.1.2.dist-info/WHEEL
human_seconds-0.1.2.dist-info/top_level.txt
human_seconds-0.1.2.dist-info/RECORD
