Metadata-Version: 2.4
Name: human-seconds
Version: 0.1.2
Summary: Convert seconds to a human-readable time string
Home-page: https://github.com/EgbieAndersonUku1/human_seconds
Author: Egbie Uku
Author-email: egbieuku@hotmail.com
License: MIT
Requires-Python: >=3.9
License-File: LICENCE
Provides-Extra: dev
Requires-Dist: pytest; extra == "dev"
Requires-Dist: black; extra == "dev"
Requires-Dist: flake8; extra == "dev"
Dynamic: license-file
